moreniius/__init__.py
moreniius/additions.py
moreniius/moreniius.py
moreniius/nexus_structure.py
moreniius/nxoff.py
moreniius/utils.py
moreniius/writer.py
moreniius/mccode/__init__.py
moreniius/mccode/comp.py
moreniius/mccode/instance.py
moreniius/mccode/instr.py
moreniius/mccode/mccode.py
moreniius/mccode/orientation.py
moreniius-0.7.0.dist-info/METADATA
moreniius-0.7.0.dist-info/WHEEL
moreniius-0.7.0.dist-info/entry_points.txt
moreniius-0.7.0.dist-info/top_level.txt
moreniius-0.7.0.dist-info/RECORD
