Metadata-Version: 2.4
Name: moreniius
Version: 0.7.0
Author-email: Gregory Tucker <gregory.tucker@ess.eu>
Classifier: License :: OSI Approved :: BSD License
Classifier: Development Status :: 2 - Pre-Alpha
Classifier: Programming Language :: Python :: 3
Classifier: Programming Language :: Python :: 3 :: Only
Classifier: Programming Language :: Python :: 3.10
Classifier: Programming Language :: Python :: 3.11
Classifier: Programming Language :: Python :: 3.12
Classifier: Programming Language :: Python :: 3.13
Classifier: Programming Language :: Python :: 3.14
Requires-Dist: zenlog>=1.1
Requires-Dist: platformdirs>=3.11
Requires-Dist: mccode-antlr[hdf5]>=0.17.0
Requires-Dist: nexusformat>=1.0.6
Requires-Dist: networkx
